theia/__init__.py
theia/data_manager.py
theia/api/__init__.py
theia/api/internal.py
theia/cli/__init__.py
theia/cli/cli.py
theia/data/__init__.py
theia/ml/__init__.py
theia/ml/explained_reaction.py
theia/ml/inference_reaction_dataset.py
theia/ml/mlp_classifier.py
theia/ml/reaction_dataset.py
theia/models/__init__.py
theia/web/__init__.py
theia/web/helpers.py
theia/web/predict.py
theia/web/run.py
theia/web/search.py
theia/web/static/bulma-tabs.js
theia/web/static/notemplate.js
theia/web/static/stackedbar.css
theia/web/static/style.css
theia/web/static/theia_wiki.jpg
theia/web/static/favicon/android-chrome-192x192.png
theia/web/static/favicon/android-chrome-512x512.png
theia/web/static/favicon/apple-touch-icon.png
theia/web/static/favicon/browserconfig.xml
theia/web/static/favicon/favicon-16x16.png
theia/web/static/favicon/favicon-32x32.png
theia/web/static/favicon/favicon.ico
theia/web/static/favicon/mstile-150x150.png
theia/web/static/favicon/safari-pinned-tab.svg
theia/web/static/favicon/site.webmanifest
theia/web/static/img/25.png
theia/web/static/img/38.png
theia/web/static/img/6.png
theia/web/static/img/chemistry.gif
theia/web/static/img/dot-grid.png
theia/web/static/img/loader.gif
theia/web/static/img/memphis-mini.webp
theia/web/static/img/topography.webp
theia/web/static/img/wavy-dots.webp
theia/web/static/img/white-waves.png
theia/web/static/ketcher/apple-touch-icon.png
theia/web/static/ketcher/asset-manifest.json
theia/web/static/ketcher/favicon-16x16.png
theia/web/static/ketcher/favicon-32x32.png
theia/web/static/ketcher/favicon.ico
theia/web/static/ketcher/index.html
theia/web/static/ketcher/logo.svg
theia/web/static/ketcher/manifest.json
theia/web/static/ketcher/robots.txt
theia/web/static/ketcher/static/css/main.8e693d51.css
theia/web/static/ketcher/static/js/main.027562ee.js
theia/web/static/ketcher/static/js/main.027562ee.js.LICENSE.txt
theia/web/static/ketcher/static/media/overlay.8faf238632c16c841197.svg
theia/web/static/ketcher/templates/fg.sdf
theia_pypi-0.7.1.dist-info/LICENSE
theia_pypi-0.7.1.dist-info/METADATA
theia_pypi-0.7.1.dist-info/WHEEL
theia_pypi-0.7.1.dist-info/entry_points.txt
theia_pypi-0.7.1.dist-info/top_level.txt
theia_pypi-0.7.1.dist-info/RECORD
