Metadata-Version: 2.1
Name: theia-pypi
Version: 0.7.1
Summary: Explainable prediction of EC numbers using a multilayer perceptron.
Home-page: https://github.com/daenuprobst/theia
Author: Daniel Probst
Author-email: daniel.probst@hey.com
License: MIT
Project-URL: Documentation, https://github.com/daenuprobst/theia
Project-URL: Source, https://github.com/daenuprobst/theia
Project-URL: Twitter, https://twitter.com/skepteis
Platform: any
Classifier: Development Status :: 5 - Production/Stable
Classifier: Topic :: Scientific/Engineering :: Chemistry
Classifier: Programming Language :: Python
Classifier: Programming Language :: Python :: 3
Classifier: Programming Language :: Python :: 3 :: Only
Classifier: Environment :: Console
Classifier: Intended Audience :: Science/Research
Classifier: License :: OSI Approved :: MIT License
Classifier: Operating System :: POSIX :: Linux
Classifier: Operating System :: Unix
Classifier: Operating System :: MacOS
Classifier: Operating System :: Microsoft :: Windows
Requires-Python: >=3.8
License-File: LICENSE
Requires-Dist: flask (>=3.0.0)
Requires-Dist: drfp (==0.3.6)
Requires-Dist: annoy (==1.15.0)
Requires-Dist: rdkit-pypi (>=2022.3.4)
Requires-Dist: numpy (==1.26.4)
Requires-Dist: pandas (<2.0.0)
Requires-Dist: scikit-learn (==1.1.1)
Requires-Dist: click (==8.1.3)
Requires-Dist: tqdm (>=4.64.0)
Requires-Dist: shap (==0.41.0)
Requires-Dist: torch (==1.13.1)
Requires-Dist: typer (>=0.7.0)
Requires-Dist: rich (>=13.2.0)
Requires-Dist: platformdirs (>=2.6.2)
Requires-Dist: requests (>=2.28.2)
Requires-Dist: importlib-metadata ; python_version < "3.8"
